jarvisportal/__init__.py
jarvisportal/actions.py
jarvisportal/bunch.py
jarvisportal/diffstr.py
jarvisportal/gpt.py
jarvisportal/gptexec.py
jarvisportal/jarvisportal.py
jarvisportal/listentomic.py
jarvisportal/llamaapichat.py
jarvisportal/replacelinesstr.py
jarvisportal-1.0.11.dist-info/LICENSE
jarvisportal-1.0.11.dist-info/METADATA
jarvisportal-1.0.11.dist-info/WHEEL
jarvisportal-1.0.11.dist-info/entry_points.txt
jarvisportal-1.0.11.dist-info/top_level.txt
jarvisportal-1.0.11.dist-info/RECORD
